query_debugger/__init__.py
query_debugger/query_debugger.py
django_query_debugger-0.0.4.dist-info/METADATA
django_query_debugger-0.0.4.dist-info/WHEEL
django_query_debugger-0.0.4.dist-info/top_level.txt
django_query_debugger-0.0.4.dist-info/RECORD
