Metadata-Version: 2.1
Name: django-query-debugger
Version: 0.0.4
Summary: Prints queries executed on you projects along with line traceback.
Home-page: https://github.com/nano-labs/django-query-debugger
Author: Fabio Pachelli Pacheco
Author-email: nanook.labs@gmail.com
License: MIT
Download-URL: https://github.com/nano-labs/django-query-debugger/archive/0.0.4.zip
Keywords: django query traceback print debug
Platform: UNKNOWN
Classifier: Development Status :: 3 - Alpha
Classifier: Intended Audience :: Developers
Classifier: Topic :: Software Development :: Build Tools
Classifier: License :: OSI Approved :: MIT License
Classifier: Programming Language :: Python :: 3.6
